markold/__init__.py
markold/markold.py
markold-1.3.2.dist-info/LICENSE
markold-1.3.2.dist-info/METADATA
markold-1.3.2.dist-info/WHEEL
markold-1.3.2.dist-info/top_level.txt
markold-1.3.2.dist-info/RECORD
