Metadata-Version: 2.1
Name: markold
Version: 1.3.2
Summary: An implementation of Markov chains, for sentence generation
Home-page: https://github.com/Coul33t/markold
Author: Quentin Couland
Author-email: Coulis1990@gmail.com
License: MIT
Platform: UNKNOWN
